fastapi_clean_archi/__init__.py
fastapi_clean_archi/cli.py
fastapi_clean_archi/core/__init__.py
fastapi_clean_archi/core/auth.py
fastapi_clean_archi/core/config.py
fastapi_clean_archi/core/commons/__init__.py
fastapi_clean_archi/core/commons/repository.py
fastapi_clean_archi/core/commons/service.py
fastapi_clean_archi/core/db/__init__.py
fastapi_clean_archi/core/db/base.py
fastapi_clean_archi/managements/__init__.py
fastapi_clean_archi/managements/commands/__init__.py
fastapi_clean_archi/managements/commands/add_module.py
fastapi_clean_archi/managements/commands/base.py
fastapi_clean_archi/managements/commands/makemigrations.py
fastapi_clean_archi/managements/commands/migrate.py
fastapi_clean_archi/managements/commands/runserver.py
fastapi_clean_archi/managements/commands/test.py
fastapi_clean_archi/managements/templates/__init__.py
fastapi_clean_archi/managements/templates/__init__.tmpl
fastapi_clean_archi/managements/templates/main.tmpl
fastapi_clean_archi/managements/templates/manage.tmpl
fastapi_clean_archi/managements/templates/pytest.tmpl
fastapi_clean_archi/managements/templates/app_module/__init__.tmpl
fastapi_clean_archi/managements/templates/app_module/application/__init__.tmpl
fastapi_clean_archi/managements/templates/app_module/application/service.tmpl
fastapi_clean_archi/managements/templates/app_module/domain/__init__.tmpl
fastapi_clean_archi/managements/templates/app_module/domain/entity.tmpl
fastapi_clean_archi/managements/templates/app_module/infrastructure/__init__.tmpl
fastapi_clean_archi/managements/templates/app_module/infrastructure/models.tmpl
fastapi_clean_archi/managements/templates/app_module/infrastructure/repository.tmpl
fastapi_clean_archi/managements/templates/app_module/interfaces/__init__.tmpl
fastapi_clean_archi/managements/templates/app_module/interfaces/controller.tmpl
fastapi_clean_archi/managements/templates/app_module/interfaces/schemas.tmpl
fastapi_clean_archi/managements/templates/app_module/tests/__init__.tmpl
fastapi_clean_archi-0.7.7.dist-info/licenses/LICENSE
fastapi_clean_archi-0.7.7.dist-info/METADATA
fastapi_clean_archi-0.7.7.dist-info/WHEEL
fastapi_clean_archi-0.7.7.dist-info/entry_points.txt
fastapi_clean_archi-0.7.7.dist-info/top_level.txt
fastapi_clean_archi-0.7.7.dist-info/RECORD
