Metadata-Version: 2.4
Name: fastapi-clean-archi
Version: 0.7.7
Summary: FastAPI with clean architecture
Author-email: YuJeonghoon <moning02004@naver.com>
License: The MIT License
Project-URL: Homepage, https://github.com/moning02004/fastapi-clean-archi
Project-URL: Bug Tracker, https://github.com/moning02004/fastapi-clean-archi/issues
Requires-Python: >=3.8
License-File: LICENSE
Requires-Dist: fastapi>=0.121.3
Requires-Dist: passlib
Requires-Dist: uvicorn
Requires-Dist: SQLAlchemy
Requires-Dist: PyJWT
Requires-Dist: pytest
Requires-Dist: alembic
Requires-Dist: python-dotenv
Requires-Dist: bcrypt==4.0.1
Requires-Dist: typer
Requires-Dist: httpx
Requires-Dist: argon2_cffi
Dynamic: license-file
